py_arg_reports/__init__.py
py_arg_reports/config.py
py_arg_reports/logs.py
py_arg_reports/base_reports/__init__.py
py_arg_reports/base_reports/recibo_base_1.py
py_arg_reports/reporters/__init__.py
py_arg_reports/reporters/descarga_excel.py
py_arg_reports/reporters/recibo_sueldo.py
py_arg_reports/reporters/acreditaciones/README.md
py_arg_reports/reporters/acreditaciones/__init__.py
py_arg_reports/reporters/acreditaciones/base.py
py_arg_reports/reporters/acreditaciones/data/bancos.json
py_arg_reports/reporters/acreditaciones/data/bancos.wikipedia
py_arg_reports/reporters/acreditaciones/data/sample-galicia-missing-importe-pago.json
py_arg_reports/reporters/acreditaciones/data/sample-galicia-missing-nro-cuenta.json
py_arg_reports/reporters/acreditaciones/data/sample-galicia.json
py_arg_reports/reporters/acreditaciones/data/sample-santander.json
py_arg_reports/reporters/acreditaciones/data/sample.json
py_arg_reports/reporters/acreditaciones/data/sample_santander_bad_codigo_de_pago.json
py_arg_reports/reporters/acreditaciones/galicia/__init__.py
py_arg_reports/reporters/acreditaciones/galicia/docs/README.md
py_arg_reports/reporters/acreditaciones/galicia/docs/Sueldosporarchivo.pdf
py_arg_reports/reporters/acreditaciones/galicia/docs/acreditacion-galicia-xlsx.png
py_arg_reports/reporters/acreditaciones/nacion/docs/README.md
py_arg_reports/reporters/acreditaciones/nacion/docs/detalle-registro.png
py_arg_reports/reporters/acreditaciones/santander/__init__.py
py_arg_reports/reporters/acreditaciones/santander/docs/Guia Pago Simple.xlsx
py_arg_reports/reporters/acreditaciones/santander/docs/Guía txt - Pago de Haberes y Honorarios.pdf
"py_arg_reports/reporters/acreditaciones/santander/docs/Guía txt - Pago de Proveedores, Personalizados y Seguro.pdf"
py_arg_reports/reporters/acreditaciones/santander/docs/screenshot-santander.png
py_arg_reports/reporters/f931/__init__.py
py_arg_reports/reporters/f931/reporter.py
py_arg_reports/reporters/f931/tools.py
payroll_arg_reportes-0.0.49.dist-info/METADATA
payroll_arg_reportes-0.0.49.dist-info/WHEEL
payroll_arg_reportes-0.0.49.dist-info/licenses/LICENSE
payroll_arg_reportes-0.0.49.dist-info/RECORD
