Metadata-Version: 2.4
Name: payroll_arg_reportes
Version: 0.0.49
Summary: Reportes para Payroll en Argentina
Project-URL: Homepage, https://github.com/Artimezoft/payroll_arg_reportes
Project-URL: Issues, https://github.com/Artimezoft/payroll_arg_reportes/issues
Author-email: Eugenio <coding_with@eugeniovazquez.com.ar>, Andres <andres@data99.com.ar>
Maintainer-email: Eugenio <coding_with@eugeniovazquez.com.ar>, Andres <andres@data99.com.ar>
License: MIT License
License-File: LICENSE
Classifier: License :: OSI Approved :: MIT License
Classifier: Operating System :: OS Independent
Classifier: Programming Language :: Python :: 3
Requires-Python: >=3.10
Requires-Dist: numero-a-letras>=0.0.4
Requires-Dist: openpyxl<4,>=3.1.4
Requires-Dist: reportlab<5,>=4.0.8
Requires-Dist: xlsxwriter<4,>=3.2.0
